autodatadictionary/__init__.py
autodatadictionary/autodatadictionary.py
autodatadictionary/analysis/__init__.py
autodatadictionary/analysis/dictionarygenerator.py
autodatadictionary/db/__init__.py
autodatadictionary/db/sqlalchemydb.py
autodatadictionary/preperation/__init__.py
autodatadictionary/preperation/dataprep.py
autodatadictionary/utils/__init__.py
autodatadictionary/utils/dataloader.py
autodatadictionary-0.0.7.dist-info/LICENSE
autodatadictionary-0.0.7.dist-info/METADATA
autodatadictionary-0.0.7.dist-info/WHEEL
autodatadictionary-0.0.7.dist-info/top_level.txt
autodatadictionary-0.0.7.dist-info/RECORD
