Metadata-Version: 2.1
Name: autodatadictionary
Version: 0.0.7
Summary: Generate automated data dictionary from files and databases
Home-page: https://github.com/bahadirhanfiliz/autodatadictionary
Author: Bahadirhan Filiz
Author-email: bahadirhanf@gmail.com
License: UNKNOWN
Project-URL: Bug Tracker, https://github.com/bahadirhanfiliz/autodatadictionary/issues
Platform: UNKNOWN
Classifier: Programming Language :: Python :: 3
Classifier: License :: OSI Approved :: MIT License
Classifier: Operating System :: OS Independent
Requires-Python: >=3.6
License-File: LICENSE
